clustermap_imshow/__init__.py
clustermap_imshow/patch.py
clustermap_imshow-0.1.1.dist-info/METADATA
clustermap_imshow-0.1.1.dist-info/WHEEL
clustermap_imshow-0.1.1.dist-info/top_level.txt
clustermap_imshow-0.1.1.dist-info/RECORD
