Metadata-Version: 2.4
Name: clustermap-imshow
Version: 0.1.1
Summary: Monkey patch for seaborn clustermap to use imshow
Requires-Python: >=3.11
Requires-Dist: scipy>=1.17.0
Requires-Dist: seaborn>=0.13.2
